{"3rHNjJVOC+XcHZIpVDpmDQ==":"dscf0037-2000x1500.jpg","Ksfg1RCTzpY0/chRKSxk+w==":"dscf0135-506x380.jpg","CDIlRPo+dWu5nnUFWFDRcQ==":"dscf0135-506x380.jpeg","ZTRqDEBYEfS9kCf+b8yBmA==":"dscf0135-1-506x380.jpeg","jj/F8R2sj50fSLcSB0Ko4g==":"p_20200102-124423-506x900.jpeg","pNIfsPfoQ5JRBIJTjY7DZw==":"p_20190818-170559-506x285.jpeg","cS+kBHVuClhgXEoXrfvFNg==":"dscf0026-506x380.jpeg","ZRWTDK42+1b2AuadEBoQQA==":"dscf0033-3648x2736.jpg","LFSgGXCEACgBprJb7cKuQw==":"p_20200704-180929-696x392.jpeg","PPu5gM4hxIQ9Q9741+YrSg==":"p_20200704-181001-696x392.jpeg","HzRkUEaz5JKXjAEztj3ENQ==":"p_20200704-181032-696x392.jpeg","Y4xRl6S6exIBG2darhcsNw==":"p_20200704-181214-696x1237.jpeg","hI4Og9sHeSBhUs5PZXFI7Q==":"p_20200704-181245-696x392.jpeg","6rXe6OGu60b7qHLuY43jRQ==":"p_20200704-181436-4096x2304.jpg","jecVbjbFpUaUxZdHd04OMg==":"p_20200704-181436-4096x2304.jpeg","zcLkUDGgXr5vj/qc0zw8qg==":"p_20200704-181459-696x1237.jpeg","veL0LcT8/2yijMd3BepTyg==":"dscf0037-3648x2736.jpg","n5PfcaZpJZnfGjSlRlzj0Q==":"p_20200704-190608-1268x713.jpg","5Es2Qb3Zmw7aKR3y/octcA==":"p_20200704-211813-1268x713.jpg","kyma/AWzrynwDeA0EOQ6Dw==":"p_20200704-211813-1268x713.jpeg","0RwxQVjxD+uAx+BE/0+f0g==":"p_20200704-212051-1268x713.jpeg","vps90O4Q+HjA4LVmVn+ceg==":"p_20200704-212558-1268x2254.jpeg","1xL2hbHyG7bldeTuBj48IQ==":"p_20200704-185925-1268x713.jpeg","gY3OiVP5Q3YdLO528HCyQg==":"p_20200704-212559-1268x2254.jpeg","gxnr+B/9DwbmcZ75LFqAEQ==":"p_20200704-185926-1268x713.jpeg","29f7NIXPTH+lcJfXGwH5OA==":"p_20200704-212560-1268x2254.jpeg","i7RysrtCSChnwVlL4F0xqg==":"p_20200704-212561-1268x2254.jpeg","K8D6LC6q9kkcFt41W1Qvbg==":"p_20200704-185927-1268x713.jpeg","gUHmmXJmJQxKJPZO+rKXeA==":"p_20200704-190033-1268x2254.jpeg","VGMp+qUSA/kQ1zKkfMsd9A==":"p_20200704-190112-1268x713.jpeg","GGxCEnE6IeK9tc2nDBu9DA==":"p_20200704-212814-4096x2304.jpg","IeTathYdLbqBgc+dZq1lwg==":"p_20200704-212814-4096x2304.jpeg","O8r/UXnuN2/zizOVgPE6Pg==":"p_20200704-190555-4096x2304.jpg","xIFttsejqu0+mvAABDMK6g==":"p_20200704-190555-4096x2304.jpeg","Nzoc/FK4irWb8GYdQwslYg==":"dscf0075a-2000x1500.jpeg","lsqxV1yrmuUWjCUWijTycw==":"dscf0075a-1-2000x1500.jpeg","/Seq7ozuS43IyFdJGdko0A==":"dscf0039a-2000x1500.jpg","aqmcbfYOtFQZGTuED5C+kw==":"rabbit-90x100.png","pNigOQxdExNJdu4oAEh9GA==":"nyuszikon-90x82.jpg","WljhFHvBbvyh6pneIaPRlQ==":"nyuszikon-90x82.jpeg","7i8VxQF3AkbND6+6qwexnA==":"nyuszikon-1-90x82.jpeg","uYjcK40WFfGBddp5J9yVrw==":"nyuszikon-90x90.jpeg","/wMiohDZYClQogxGxL1VnQ==":"nyuszikon-1-90x90.jpeg","YCYtavwvqdpvRx9sj5+hLg==":"dscf0033-1-3648x2736.jpg"}